README.rst
setup.py
pythrottle/__init__.py
pythrottle/rate_meter.py
pythrottle/throttle.py
pythrottle.egg-info/PKG-INFO
pythrottle.egg-info/SOURCES.txt
pythrottle.egg-info/dependency_links.txt
pythrottle.egg-info/top_level.txt