Metadata-Version: 2.1
Name: pythrottle
Version: 0.1.1
Summary: Set of tools for throttling and controlling the execution timing of Python code.
Home-page: https://github.com/flusflas/pythrottle
Author: Flus Flas
Author-email: aflusflas@gmail.com
License: UNKNOWN
Keywords: throttle,throttling,time,timing,rate
Platform: UNKNOWN
Classifier: Development Status :: 4 - Beta
Classifier: Intended Audience :: Developers
Classifier: License :: OSI Approved :: MIT License
Classifier: Operating System :: OS Independent
Classifier: Programming Language :: Python
Classifier: Programming Language :: Python :: 3
Classifier: Programming Language :: Python :: 3.6
Classifier: Programming Language :: Python :: 3.7
Classifier: Programming Language :: Python :: 3.8
Classifier: Topic :: Software Development :: Libraries
Requires-Python: >=3.6
